[
    {
        "id":"0",
        "fullName":"firstName lastName",
        "phoneNumber":"0927784322",
        "email":"example@example.com",
        "status":"Active",
        "posted":22
    },
    {
        "id":"1",
        "fullName":"firstName lastName",
        "phoneNumber":"0927784322",
        "email":"example@example.com",
        "status":"Active",
        "posted":22
    },
    {
        "id":"2",
        "fullName":"firstName lastName",
        "phoneNumber":"0927784322",
        "email":"example@example.com",
        "status":"Active",
        "posted":22
    }, {
        "id":"3",
        "fullName":"firstName lastName",
        "phoneNumber":"0927784322",
        "email":"example@example.com",
        "status":"Active",
        "posted":22
    },
    {
        "id":"4",
        "fullName":"firstName lastName",
        "phoneNumber":"0927784322",
        "email":"example@example.com",
        "status":"Active",
        "posted":22
    },
    {
        "id":"5",
        "fullName":"firstName lastName",
        "phoneNumber":"0927784322",
        "email":"example@example.com",
        "status":"Active",
        "posted":22
    }
]